DESCRIPTION.rst
MANIFEST.in
README.rst
setup.py
ZeoRawData/BaseLink.py
ZeoRawData/Parser.py
ZeoRawData/Utility.py
ZeoRawData/__init__.py
ZeoRawData.egg-info/PKG-INFO
ZeoRawData.egg-info/SOURCES.txt
ZeoRawData.egg-info/dependency_links.txt
ZeoRawData.egg-info/requires.txt
ZeoRawData.egg-info/top_level.txt