Metadata-Version: 1.1
Name: ZeoRawData
Version: 2.0
Summary: Zeo Raw Data Library
Home-page: http://www.sleepstreamonline.com/rdl/
Author: Brian Schiffer
Author-email: brianschifferece@gmail.com
License: UNKNOWN
Keywords: zeo
Platform: UNKNOWN
Classifier: Development Status :: 7 - Inactive
Classifier: Intended Audience :: Developers
Classifier: Topic :: Software Development :: Libraries
Classifier: License :: Other/Proprietary License
Classifier: Programming Language :: Python :: 2
